credisdict/CRedisDict.py
credisdict/__init__.py
credisdict-1.0.0.dist-info/LICENSE
credisdict-1.0.0.dist-info/METADATA
credisdict-1.0.0.dist-info/WHEEL
credisdict-1.0.0.dist-info/top_level.txt
credisdict-1.0.0.dist-info/RECORD
